yt_info_extract/__init__.py
yt_info_extract/cli.py
yt_info_extract/extractor.py
yt_info_extract/utils.py
yt_info_extract-1.1.0.dist-info/METADATA
yt_info_extract-1.1.0.dist-info/WHEEL
yt_info_extract-1.1.0.dist-info/entry_points.txt
yt_info_extract-1.1.0.dist-info/licenses/LICENSE
yt_info_extract-1.1.0.dist-info/RECORD
