Metadata-Version: 2.4
Name: yt-info-extract
Version: 1.1.0
Summary: Extract video information from YouTube videos including title, description, channel name, publication date and views
Project-URL: Homepage, https://github.com/sinjab/yt-info-extract
Project-URL: Documentation, https://github.com/sinjab/yt-info-extract#readme
Project-URL: Repository, https://github.com/sinjab/yt-info-extract
Project-URL: Issues, https://github.com/sinjab/yt-info-extract/issues
Author-email: Khaldoon Sinjab <sinjab@gmail.com>
License: MIT License
License-File: LICENSE
Keywords: api,automation,channel,cli,description,extract,information,metadata,title,video,views,youtube
Classifier: Development Status :: 5 - Production/Stable
Classifier: Intended Audience :: Developers
Classifier: Intended Audience :: End Users/Desktop
Classifier: License :: OSI Approved :: MIT License
Classifier: Operating System :: OS Independent
Classifier: Programming Language :: Python :: 3
Classifier: Programming Language :: Python :: 3.8
Classifier: Programming Language :: Python :: 3.9
Classifier: Programming Language :: Python :: 3.10
Classifier: Programming Language :: Python :: 3.11
Classifier: Programming Language :: Python :: 3.12
Classifier: Topic :: Internet :: WWW/HTTP
Classifier: Topic :: Multimedia :: Video
Classifier: Topic :: Software Development :: Libraries :: Python Modules
Classifier: Topic :: Text Processing
Requires-Python: >=3.8
Requires-Dist: google-api-python-client>=2.100.0
Requires-Dist: pytubefix>=6.0.0
Requires-Dist: requests>=2.31.0
Requires-Dist: yt-dlp>=2023.7.6
Provides-Extra: dev
Requires-Dist: black>=22.0.0; extra == 'dev'
Requires-Dist: build>=0.10.0; extra == 'dev'
Requires-Dist: isort>=5.0.0; extra == 'dev'
Requires-Dist: pytest>=7.0.0; extra == 'dev'
Requires-Dist: twine>=4.0.0; extra == 'dev'
